{
  "NVDA": {
    "symbol": "NVDA",
    "price": 194.97,
    "changePct": 1.267334960785331,
    "fetchedAt": "2026-06-29T20:54:14.911Z"
  },
  "MSFT": {
    "symbol": "MSFT",
    "price": 368.57,
    "changePct": -1.1797195484891638,
    "fetchedAt": "2026-06-29T20:54:14.915Z"
  },
  "GOOG": {
    "symbol": "GOOG",
    "price": 351.28,
    "changePct": 4.95682571932235,
    "fetchedAt": "2026-06-29T20:54:15.154Z"
  },
  "META": {
    "symbol": "META",
    "price": 562.6,
    "changePct": 2.2444343480236295,
    "fetchedAt": "2026-06-29T20:54:15.118Z"
  },
  "AMZN": {
    "symbol": "AMZN",
    "price": 240.14,
    "changePct": 3.20168464480639,
    "fetchedAt": "2026-06-29T20:54:15.363Z"
  }
}