{
  "NVDA": {
    "symbol": "NVDA",
    "price": 212.5,
    "changePct": 0.33050047214352624,
    "fetchedAt": "2026-07-16T11:48:28.661Z"
  },
  "MSFT": {
    "symbol": "MSFT",
    "price": 395.63,
    "changePct": 2.7797261839815004,
    "fetchedAt": "2026-07-16T11:48:28.657Z"
  },
  "GOOG": {
    "symbol": "GOOG",
    "price": 370.21,
    "changePct": 3.604511236112276,
    "fetchedAt": "2026-07-16T11:48:28.644Z"
  },
  "META": {
    "symbol": "META",
    "price": 681.31,
    "changePct": 3.0663802493041246,
    "fetchedAt": "2026-07-16T11:48:28.675Z"
  },
  "AMZN": {
    "symbol": "AMZN",
    "price": 254.96,
    "changePct": 3.0183037698492865,
    "fetchedAt": "2026-07-16T11:48:28.757Z"
  },
  "AMD": {
    "symbol": "AMD",
    "price": 529.14,
    "changePct": -3.464506595150787,
    "fetchedAt": "2026-07-16T11:48:28.741Z"
  },
  "TSM": {
    "symbol": "TSM",
    "price": 419.48,
    "changePct": -0.21646566283688196,
    "fetchedAt": "2026-07-16T11:48:28.971Z"
  },
  "AVGO": {
    "symbol": "AVGO",
    "price": 394.28,
    "changePct": 1.3286731258512912,
    "fetchedAt": "2026-07-16T11:48:28.932Z"
  }
}